salesforce_bulk/__init__.py
salesforce_bulk/__version__.py
salesforce_bulk/bulk_states.py
salesforce_bulk/csv_adapter.py
salesforce_bulk/salesforce_bulk.py
salesforce_bulk/util.py
salesforce_bulk_2_7-2.2.8.dist-info/LICENSE
salesforce_bulk_2_7-2.2.8.dist-info/METADATA
salesforce_bulk_2_7-2.2.8.dist-info/WHEEL
salesforce_bulk_2_7-2.2.8.dist-info/top_level.txt
salesforce_bulk_2_7-2.2.8.dist-info/RECORD
