Metadata-Version: 2.1
Name: salesforce-bulk-2-7
Version: 2.2.8
Summary: Python interface to the Salesforce.com Bulk API.
Home-page: https://github.com/taulia/salesforce-bulk-2-7
Author: Scott Persinger
Author-email: scottp@heroku.com
License: MIT
Download-URL: https://github.com/taulia/salesforce-bulk-2-7/archive/2.1.1.tar.gz
Platform: UNKNOWN
Classifier: Development Status :: 5 - Production/Stable
Classifier: Intended Audience :: Developers
Classifier: Natural Language :: English
Classifier: License :: OSI Approved :: MIT License
Classifier: Programming Language :: Python
Classifier: Programming Language :: Python :: 2.7
Requires-Dist: six
Requires-Dist: requests (>=2.2.1)
Requires-Dist: unicodecsv (>=0.14.1)
Requires-Dist: simple-salesforce-2-7 (>=1.0.2)
